pwrdrvr/microapps/cdk/__init__.py
pwrdrvr/microapps/cdk/py.typed
pwrdrvr/microapps/cdk/_jsii/__init__.py
pwrdrvr/microapps/cdk/_jsii/microapps-cdk@1.0.3.jsii.tgz
pwrdrvr.microapps.cdk-1.0.3.dist-info/LICENSE
pwrdrvr.microapps.cdk-1.0.3.dist-info/METADATA
pwrdrvr.microapps.cdk-1.0.3.dist-info/WHEEL
pwrdrvr.microapps.cdk-1.0.3.dist-info/top_level.txt
pwrdrvr.microapps.cdk-1.0.3.dist-info/RECORD
