Metadata-Version: 2.1
Name: pwrdrvr.microapps.cdk
Version: 1.0.3
Summary: MicroApps framework, by PwrDrvr LLC, delivered as an AWS CDK construct that provides the DynamoDB, Router service, Deploy service, API Gateway, and CloudFront distribution.
Home-page: https://github.com/pwrdrvr/microapps-core
Author: PwrDrvr LLC<harold@pwrdrvr.com>
License: MIT
Project-URL: Source, https://github.com/pwrdrvr/microapps-core
Classifier: Intended Audience :: Developers
Classifier: Operating System :: OS Independent
Classifier: Programming Language :: JavaScript
Classifier: Programming Language :: Python :: 3 :: Only
Classifier: Programming Language :: Python :: 3.8
Classifier: Programming Language :: Python :: 3.9
Classifier: Programming Language :: Python :: 3.10
Classifier: Programming Language :: Python :: 3.11
Classifier: Typing :: Typed
Classifier: Development Status :: 4 - Beta
Classifier: License :: OSI Approved
Requires-Python: ~=3.8
License-File: LICENSE
Requires-Dist: aws-cdk-lib <3.0.0,>=2.95.0
Requires-Dist: constructs <11.0.0,>=10.0.5
Requires-Dist: jsii <2.0.0,>=1.97.0
Requires-Dist: publication >=0.0.3
Requires-Dist: typeguard ~=2.13.3
